{
  "filePath": ".spec-workflow/specs/device-hotplug-state-management/requirements.md",
  "currentVersion": 2,
  "snapshots": [
    {
      "version": 1,
      "filename": "snapshot-001.json",
      "timestamp": "2025-12-03T14:42:05.341Z",
      "trigger": "initial",
      "approvalId": "approval_1764772925296_xyrekwkj7",
      "approvalTitle": "Requirements: Device Hotplug State Management"
    },
    {
      "version": 2,
      "filename": "snapshot-002.json",
      "timestamp": "2025-12-03T14:51:28.322Z",
      "trigger": "approved",
      "approvalId": "approval_1764772925296_xyrekwkj7",
      "approvalTitle": "Requirements: Device Hotplug State Management"
    }
  ]
}